MassiveQC/FeatureCounts.py
MassiveQC/IsoDetect.py
MassiveQC/MultiProcess.py
MassiveQC/SingleProcess.py
MassiveQC/__init__.py
MassiveQC/atropos.py
MassiveQC/build_features.py
MassiveQC/check_fq.py
MassiveQC/collectrnaseqmetrics.py
MassiveQC/command.py
MassiveQC/detection.py
MassiveQC/fastq.py
MassiveQC/fastq_screen.py
MassiveQC/feature_store.py
MassiveQC/get_sra.py
MassiveQC/hisat2.py
MassiveQC/iforest.py
MassiveQC/markduplicates.py
MassiveQC/parser.py
MassiveQC/plot.py
MassiveQC-0.1.2.dist-info/METADATA
MassiveQC-0.1.2.dist-info/WHEEL
MassiveQC-0.1.2.dist-info/entry_points.txt
MassiveQC-0.1.2.dist-info/top_level.txt
MassiveQC-0.1.2.dist-info/RECORD
